{"v":"5.4.1","fr":30,"ip":0,"op":60,"w":750,"h":940,"nm":"Liveness Animation Oct 2019 @2x Part 2","ddd":0,"assets":[],"layers":[{"ddd":0,"ind":1,"ty":4,"nm":"Head Outline Outlines","sr":1,"ks":{"o":{"a":1,"k":[{"i":{"x":[0.667],"y":[1]},"o":{"x":[0.333],"y":[0]},"n":["0p667_1_0p333_0"],"t":-15,"s":[0],"e":[100]},{"t":0}],"ix":11},"r":{"a":0,"k":0,"ix":10},"p":{"a":0,"k":[375,455,0],"ix":2},"a":{"a":0,"k":[161,233.5,0],"ix":1},"s":{"a":0,"k":[125,125,100],"ix":6}},"ao":0,"shapes":[{"ty":"gr","it":[{"ind":0,"ty":"sh","ix":1,"ks":{"a":0,"k":{"i":[[0,0],[10.103,10.623],[1.217,7.822],[0.585,11.854]],"o":[[-24.688,-7.549],[-5.475,-5.757],[-0.674,-4.331],[0,0]],"v":[[31.81,34.816],[-20.376,7.558],[-29.921,-10.539],[-31.81,-34.816]],"c":false},"ix":2},"nm":"Path 1","mn":"ADBE Vector Shape - Group","hd":false},{"ty":"st","c":{"a":0,"k":[1,1,1,1],"ix":3},"o":{"a":0,"k":100,"ix":4},"w":{"a":0,"k":6.498,"ix":5},"lc":2,"lj":2,"nm":"Stroke 1","mn":"ADBE Vector Graphic - Stroke","hd":false},{"ty":"tr","p":{"a":0,"k":[273.039,420.294],"ix":2},"a":{"a":0,"k":[0,0],"ix":1},"s":{"a":0,"k":[100,100],"ix":3},"r":{"a":0,"k":0,"ix":6},"o":{"a":0,"k":100,"ix":7},"sk":{"a":0,"k":0,"ix":4},"sa":{"a":0,"k":0,"ix":5},"nm":"Transform"}],"nm":"Group 1","np":2,"cix":2,"ix":1,"mn":"ADBE Vector Group","hd":false},{"ty":"gr","it":[{"ind":0,"ty":"sh","ix":1,"ks":{"a":0,"k":{"i":[[0,0],[-23.813,-36.657],[-1.857,-19.739],[0,-6.97],[-0.825,-4.913],[-6.474,0.415],[-0.644,-8.596],[0.857,-3.461],[0,-4.31],[9.35,-0.588],[-0.767,3.899],[0.199,-0.525],[17.493,-19.472],[24.522,-0.431]],"o":[[50.16,0.612],[14.089,21.687],[2.852,30.306],[0,7.673],[0.568,-15.768],[4.655,-0.298],[0.699,9.336],[-1.645,6.648],[0,4.31],[-5.788,0.364],[0.256,-1.301],[-9.665,43.896],[-26.24,29.208],[0,0]],"v":[[-74.657,-208.157],[36.303,-152.252],[54.458,-89.88],[54.458,-26.956],[55.696,-8.078],[66.26,-32.352],[73.958,-18.579],[72.502,6.876],[63.961,48.845],[53.768,67.381],[48.844,68.544],[48.929,67.381],[8.192,162.432],[-74.657,208.157]],"c":false},"ix":2},"nm":"Path 1","mn":"ADBE Vector Shape - Group","hd":false},{"ty":"st","c":{"a":0,"k":[1,1,1,1],"ix":3},"o":{"a":0,"k":100,"ix":4},"w":{"a":0,"k":6.498,"ix":5},"lc":2,"lj":2,"nm":"Stroke 1","mn":"ADBE Vector Graphic - Stroke","hd":false},{"ty":"tr","p":{"a":0,"k":[235.573,220.157],"ix":2},"a":{"a":0,"k":[0,0],"ix":1},"s":{"a":0,"k":[100,100],"ix":3},"r":{"a":0,"k":0,"ix":6},"o":{"a":0,"k":100,"ix":7},"sk":{"a":0,"k":0,"ix":4},"sa":{"a":0,"k":0,"ix":5},"nm":"Transform"}],"nm":"Group 2","np":2,"cix":2,"ix":2,"mn":"ADBE Vector Group","hd":false},{"ty":"gr","it":[{"ind":0,"ty":"sh","ix":1,"ks":{"a":0,"k":{"i":[[0,0],[-10.103,10.623],[-1.217,7.822],[-0.585,11.854]],"o":[[24.688,-7.549],[5.475,-5.757],[0.674,-4.331],[0,0]],"v":[[-31.81,34.816],[20.376,7.558],[29.921,-10.539],[31.81,-34.816]],"c":false},"ix":2},"nm":"Path 1","mn":"ADBE Vector Shape - Group","hd":false},{"ty":"st","c":{"a":0,"k":[1,1,1,1],"ix":3},"o":{"a":0,"k":100,"ix":4},"w":{"a":0,"k":6.498,"ix":5},"lc":2,"lj":2,"nm":"Stroke 1","mn":"ADBE Vector Graphic - Stroke","hd":false},{"ty":"tr","p":{"a":0,"k":[48.801,420.294],"ix":2},"a":{"a":0,"k":[0,0],"ix":1},"s":{"a":0,"k":[100,100],"ix":3},"r":{"a":0,"k":0,"ix":6},"o":{"a":0,"k":100,"ix":7},"sk":{"a":0,"k":0,"ix":4},"sa":{"a":0,"k":0,"ix":5},"nm":"Transform"}],"nm":"Group 3","np":2,"cix":2,"ix":3,"mn":"ADBE Vector Group","hd":false},{"ty":"gr","it":[{"ind":0,"ty":"sh","ix":1,"ks":{"a":0,"k":{"i":[[0,0],[23.813,-36.657],[1.857,-19.739],[0,-6.97],[0.825,-4.913],[6.474,0.415],[0.644,-8.596],[-0.857,-3.461],[0,-4.31],[-9.35,-0.588],[0.767,3.899],[-0.199,-0.525],[-17.493,-19.472],[-24.522,-0.431]],"o":[[-50.16,0.612],[-14.089,21.687],[-2.852,30.306],[0,7.673],[-0.568,-15.768],[-4.655,-0.298],[-0.699,9.336],[1.645,6.648],[0,4.31],[5.788,0.364],[-0.256,-1.301],[9.665,43.896],[26.24,29.208],[0,0]],"v":[[74.657,-208.157],[-36.303,-152.252],[-54.458,-89.88],[-54.458,-26.956],[-55.696,-8.078],[-66.26,-32.352],[-73.958,-18.579],[-72.502,6.876],[-63.961,48.845],[-53.768,67.381],[-48.844,68.544],[-48.929,67.381],[-8.192,162.432],[74.657,208.157]],"c":false},"ix":2},"nm":"Path 1","mn":"ADBE Vector Shape - Group","hd":false},{"ty":"st","c":{"a":0,"k":[1,1,1,1],"ix":3},"o":{"a":0,"k":100,"ix":4},"w":{"a":0,"k":6.498,"ix":5},"lc":2,"lj":2,"nm":"Stroke 1","mn":"ADBE Vector Graphic - Stroke","hd":false},{"ty":"tr","p":{"a":0,"k":[86.267,220.157],"ix":2},"a":{"a":0,"k":[0,0],"ix":1},"s":{"a":0,"k":[100,100],"ix":3},"r":{"a":0,"k":0,"ix":6},"o":{"a":0,"k":100,"ix":7},"sk":{"a":0,"k":0,"ix":4},"sa":{"a":0,"k":0,"ix":5},"nm":"Transform"}],"nm":"Group 4","np":2,"cix":2,"ix":4,"mn":"ADBE Vector Group","hd":false}],"ip":-15,"op":60,"st":-15,"bm":0},{"ddd":0,"ind":2,"ty":4,"nm":"IPV Liveness Phone Outlines","sr":1,"ks":{"o":{"a":1,"k":[{"i":{"x":[0.667],"y":[1]},"o":{"x":[0.333],"y":[0]},"n":["0p667_1_0p333_0"],"t":-15,"s":[0],"e":[100]},{"t":0}],"ix":11},"r":{"a":0,"k":0,"ix":10},"p":{"a":0,"k":[375,459,0],"ix":2},"a":{"a":0,"k":[371.5,599,0],"ix":1},"s":{"a":0,"k":[91.585,91.585,100],"ix":6}},"ao":0,"shapes":[{"ty":"gr","it":[{"ind":0,"ty":"sh","ix":1,"ks":{"a":0,"k":{"i":[[0,3.657],[0,0],[-3.159,0],[0,-3.656],[0,0],[3.159,0]],"o":[[0,0],[0,-3.656],[3.159,0],[0,0],[0,3.657],[-3.159,0]],"v":[[201.057,-298.753],[201.057,-325.122],[206.779,-331.744],[212.5,-325.122],[212.5,-298.753],[206.779,-292.131]],"c":true},"ix":2},"nm":"Path 1","mn":"ADBE Vector Shape - Group","hd":true},{"ind":1,"ty":"sh","ix":2,"ks":{"a":0,"k":{"i":[[0,3.658],[0,0],[-3.159,0],[0,-3.657],[0,0],[3.159,0]],"o":[[0,0],[0,-3.657],[3.159,0],[0,0],[0,3.658],[-3.159,0]],"v":[[201.057,-246.017],[201.057,-272.384],[206.779,-279.006],[212.5,-272.384],[212.5,-246.017],[206.779,-239.395]],"c":true},"ix":2},"nm":"Path 2","mn":"ADBE Vector Shape - Group","hd":true},{"ind":2,"ty":"sh","ix":3,"ks":{"a":0,"k":{"i":[[0,3.657],[0,0],[-3.159,0],[0,-3.657],[0,0],[3.159,0]],"o":[[0,0],[0,-3.657],[3.159,0],[0,0],[0,3.657],[-3.159,0]],"v":[[201.057,-193.279],[201.057,-219.648],[206.779,-226.27],[212.5,-219.648],[212.5,-193.279],[206.779,-186.657]],"c":true},"ix":2},"nm":"Path 3","mn":"ADBE Vector Shape - Group","hd":true},{"ind":3,"ty":"sh","ix":4,"ks":{"a":0,"k":{"i":[[0,3.657],[0,0],[-3.159,0],[0,-3.657],[0,0],[3.159,0]],"o":[[0,0],[0,-3.657],[3.159,0],[0,0],[0,3.657],[-3.159,0]],"v":[[201.057,-140.543],[201.057,-166.911],[206.779,-173.533],[212.5,-166.911],[212.5,-140.543],[206.779,-133.92]],"c":true},"ix":2},"nm":"Path 4","mn":"ADBE Vector Shape - Group","hd":true},{"ind":4,"ty":"sh","ix":5,"ks":{"a":0,"k":{"i":[[0,3.657],[0,0],[-3.159,0],[0,-3.657],[0,0],[3.159,0]],"o":[[0,0],[0,-3.657],[3.159,0],[0,0],[0,3.657],[-3.159,0]],"v":[[201.057,-87.806],[201.057,-114.175],[206.779,-120.796],[212.5,-114.175],[212.5,-87.806],[206.779,-81.184]],"c":true},"ix":2},"nm":"Path 5","mn":"ADBE Vector Shape - Group","hd":true},{"ind":5,"ty":"sh","ix":6,"ks":{"a":0,"k":{"i":[[0,3.656],[0,0],[-3.159,0],[0,-3.657],[0,0],[3.159,0]],"o":[[0,0],[0,-3.657],[3.159,0],[0,0],[0,3.656],[-3.159,0]],"v":[[201.057,-35.069],[201.057,-61.437],[206.779,-68.059],[212.5,-61.437],[212.5,-35.069],[206.779,-28.448]],"c":true},"ix":2},"nm":"Path 6","mn":"ADBE Vector Shape - Group","hd":true},{"ind":6,"ty":"sh","ix":7,"ks":{"a":0,"k":{"i":[[0,3.657],[0,0],[-3.159,0],[0,-3.656],[0,0],[3.159,0]],"o":[[0,0],[0,-3.656],[3.159,0],[0,0],[0,3.657],[-3.159,0]],"v":[[201.057,17.668],[201.057,-8.701],[206.779,-15.323],[212.5,-8.701],[212.5,17.668],[206.779,24.29]],"c":true},"ix":2},"nm":"Path 7","mn":"ADBE Vector Shape - Group","hd":true},{"ind":7,"ty":"sh","ix":8,"ks":{"a":0,"k":{"i":[[0,3.657],[0,0],[-3.159,0],[0,-3.657],[0,0],[3.159,0]],"o":[[0,0],[0,-3.657],[3.159,0],[0,0],[0,3.657],[-3.159,0]],"v":[[201.057,70.404],[201.057,44.036],[206.779,37.414],[212.5,44.036],[212.5,70.404],[206.779,77.026]],"c":true},"ix":2},"nm":"Path 8","mn":"ADBE Vector Shape - Group","hd":true},{"ind":8,"ty":"sh","ix":9,"ks":{"a":0,"k":{"i":[[0,3.657],[0,0],[-3.159,0],[0,-3.657],[0,0],[3.159,0]],"o":[[0,0],[0,-3.657],[3.159,0],[0,0],[0,3.657],[-3.159,0]],"v":[[201.057,123.141],[201.057,96.773],[206.779,90.151],[212.5,96.773],[212.5,123.141],[206.779,129.763]],"c":true},"ix":2},"nm":"Path 9","mn":"ADBE Vector Shape - Group","hd":true},{"ind":9,"ty":"sh","ix":10,"ks":{"a":0,"k":{"i":[[0,3.656],[0,0],[-3.159,0],[0,-3.658],[0,0],[3.159,0]],"o":[[0,0],[0,-3.658],[3.159,0],[0,0],[0,3.656],[-3.159,0]],"v":[[201.057,175.879],[201.057,149.51],[206.779,142.888],[212.5,149.51],[212.5,175.879],[206.779,182.5]],"c":true},"ix":2},"nm":"Path 10","mn":"ADBE Vector Shape - Group","hd":true},{"ind":10,"ty":"sh","ix":11,"ks":{"a":0,"k":{"i":[[0,3.656],[0,0],[-3.159,0],[0,-3.657],[0,0],[3.159,0]],"o":[[0,0],[0,-3.657],[3.159,0],[0,0],[0,3.656],[-3.159,0]],"v":[[201.057,228.615],[201.057,202.246],[206.779,195.624],[212.5,202.246],[212.5,228.615],[206.779,235.236]],"c":true},"ix":2},"nm":"Path 11","mn":"ADBE Vector Shape - Group","hd":true},{"ind":11,"ty":"sh","ix":12,"ks":{"a":0,"k":{"i":[[0,3.658],[0,0],[-3.159,0],[0,-3.656],[0,0],[3.159,0]],"o":[[0,0],[0,-3.656],[3.159,0],[0,0],[0,3.658],[-3.159,0]],"v":[[201.057,281.351],[201.057,254.982],[206.779,248.36],[212.5,254.982],[212.5,281.351],[206.779,287.974]],"c":true},"ix":2},"nm":"Path 12","mn":"ADBE Vector Shape - Group","hd":true},{"ind":12,"ty":"sh","ix":13,"ks":{"a":0,"k":{"i":[[0,3.657],[0,0],[-3.159,0],[0,-3.657],[0,0],[3.159,0]],"o":[[0,0],[0,-3.657],[3.159,0],[0,0],[0,3.657],[-3.159,0]],"v":[[201.057,334.088],[201.057,307.72],[206.779,301.099],[212.5,307.72],[212.5,334.088],[206.779,340.71]],"c":true},"ix":2},"nm":"Path 13","mn":"ADBE Vector Shape - Group","hd":true},{"ind":13,"ty":"sh","ix":14,"ks":{"a":0,"k":{"i":[[0,3.657],[-3.159,0],[0,0],[-0.03,-6.05],[0,0],[3.148,-0.021],[0.796,2.571],[0,0]],"o":[[0,-3.657],[0,0],[5.228,0],[0,0],[0,3.639],[-2.494,0.016],[0,0],[-3.159,0]],"v":[[180.427,-355.878],[186.149,-362.5],[202.964,-362.5],[212.5,-351.529],[212.5,-351.489],[206.812,-344.869],[201.391,-349.256],[186.149,-349.256]],"c":true},"ix":2},"nm":"Path 14","mn":"ADBE Vector Shape - Group","hd":true},{"ind":14,"ty":"sh","ix":15,"ks":{"a":0,"k":{"i":[[0,3.657],[-3.16,0],[0,0],[0,-3.656],[3.16,0],[0,0]],"o":[[0,-3.656],[0,0],[3.16,0],[0,3.657],[0,0],[-3.16,0]],"v":[[172.68,355.878],[178.402,349.257],[201.184,349.257],[206.906,355.878],[201.184,362.5],[178.402,362.5]],"c":true},"ix":2},"nm":"Path 15","mn":"ADBE Vector Shape - Group","hd":true},{"ind":15,"ty":"sh","ix":16,"ks":{"a":0,"k":{"i":[[0,3.657],[-3.16,0],[0,0],[0,-3.657],[3.16,0],[0,0]],"o":[[0,-3.657],[0,0],[3.16,0],[0,3.657],[0,0],[-3.16,0]],"v":[[134.862,-355.878],[140.583,-362.5],[163.366,-362.5],[169.087,-355.878],[163.366,-349.256],[140.583,-349.256]],"c":true},"ix":2},"nm":"Path 16","mn":"ADBE Vector Shape - Group","hd":true},{"ind":16,"ty":"sh","ix":17,"ks":{"a":0,"k":{"i":[[0,3.657],[-3.159,0],[0,0],[0,-3.656],[3.159,0],[0,0]],"o":[[0,-3.656],[0,0],[3.159,0],[0,3.657],[0,0],[-3.159,0]],"v":[[127.114,355.878],[132.835,349.257],[155.619,349.257],[161.34,355.878],[155.619,362.5],[132.835,362.5]],"c":true},"ix":2},"nm":"Path 17","mn":"ADBE Vector Shape - Group","hd":true},{"ind":17,"ty":"sh","ix":18,"ks":{"a":0,"k":{"i":[[0,3.657],[-3.159,0],[0,0],[0,-3.657],[3.16,0],[0,0]],"o":[[0,-3.657],[0,0],[3.16,0],[0,3.657],[0,0],[-3.159,0]],"v":[[89.296,-355.878],[95.017,-362.5],[117.8,-362.5],[123.522,-355.878],[117.8,-349.256],[95.017,-349.256]],"c":true},"ix":2},"nm":"Path 18","mn":"ADBE Vector Shape - Group","hd":true},{"ind":18,"ty":"sh","ix":19,"ks":{"a":0,"k":{"i":[[0,3.657],[-3.16,0],[0,0],[0,-3.656],[3.159,0],[0,0]],"o":[[0,-3.656],[0,0],[3.159,0],[0,3.657],[0,0],[-3.16,0]],"v":[[81.548,355.878],[87.27,349.257],[110.053,349.257],[115.774,355.878],[110.053,362.5],[87.27,362.5]],"c":true},"ix":2},"nm":"Path 19","mn":"ADBE Vector Shape - Group","hd":true},{"ind":19,"ty":"sh","ix":20,"ks":{"a":0,"k":{"i":[[0,3.657],[-3.16,0],[0,0],[0,-3.657],[3.16,0],[0,0]],"o":[[0,-3.657],[0,0],[3.16,0],[0,3.657],[0,0],[-3.16,0]],"v":[[43.73,-355.878],[49.452,-362.5],[72.234,-362.5],[77.955,-355.878],[72.234,-349.256],[49.452,-349.256]],"c":true},"ix":2},"nm":"Path 20","mn":"ADBE Vector Shape - Group","hd":true},{"ind":20,"ty":"sh","ix":21,"ks":{"a":0,"k":{"i":[[0,3.657],[-3.159,0],[0,0],[0,-3.656],[3.16,0],[0,0]],"o":[[0,-3.656],[0,0],[3.16,0],[0,3.657],[0,0],[-3.159,0]],"v":[[35.983,355.878],[41.703,349.257],[64.487,349.257],[70.208,355.878],[64.487,362.5],[41.703,362.5]],"c":true},"ix":2},"nm":"Path 21","mn":"ADBE Vector Shape - Group","hd":true},{"ind":21,"ty":"sh","ix":22,"ks":{"a":0,"k":{"i":[[0,3.657],[-3.16,0],[0,0],[0,-3.657],[3.16,0],[0,0]],"o":[[0,-3.657],[0,0],[3.16,0],[0,3.657],[0,0],[-3.16,0]],"v":[[-1.836,-355.878],[3.886,-362.5],[26.668,-362.5],[32.39,-355.878],[26.668,-349.256],[3.886,-349.256]],"c":true},"ix":2},"nm":"Path 22","mn":"ADBE Vector Shape - Group","hd":true},{"ind":22,"ty":"sh","ix":23,"ks":{"a":0,"k":{"i":[[0,3.657],[-3.16,0],[0,0],[0,-3.656],[3.16,0],[0,0]],"o":[[0,-3.656],[0,0],[3.16,0],[0,3.657],[0,0],[-3.16,0]],"v":[[-9.583,355.878],[-3.861,349.257],[18.92,349.257],[24.642,355.878],[18.92,362.5],[-3.861,362.5]],"c":true},"ix":2},"nm":"Path 23","mn":"ADBE Vector Shape - Group","hd":true},{"ind":23,"ty":"sh","ix":24,"ks":{"a":0,"k":{"i":[[0,3.657],[-3.16,0],[0,0],[0,-3.657],[3.16,0],[0,0]],"o":[[0,-3.657],[0,0],[3.16,0],[0,3.657],[0,0],[-3.16,0]],"v":[[-47.402,-355.878],[-41.68,-362.5],[-18.897,-362.5],[-13.176,-355.878],[-18.897,-349.256],[-41.68,-349.256]],"c":true},"ix":2},"nm":"Path 24","mn":"ADBE Vector Shape - Group","hd":true},{"ind":24,"ty":"sh","ix":25,"ks":{"a":0,"k":{"i":[[0,3.657],[-3.16,0],[0,0],[0,-3.656],[3.16,0],[0,0]],"o":[[0,-3.656],[0,0],[3.16,0],[0,3.657],[0,0],[-3.16,0]],"v":[[-55.15,355.878],[-49.428,349.257],[-26.645,349.257],[-20.923,355.878],[-26.645,362.5],[-49.428,362.5]],"c":true},"ix":2},"nm":"Path 25","mn":"ADBE Vector Shape - Group","hd":true},{"ind":25,"ty":"sh","ix":26,"ks":{"a":0,"k":{"i":[[0,3.657],[-3.16,0],[0,0],[0,-3.657],[3.16,0],[0,0]],"o":[[0,-3.657],[0,0],[3.16,0],[0,3.657],[0,0],[-3.16,0]],"v":[[-92.967,-355.878],[-87.246,-362.5],[-64.463,-362.5],[-58.741,-355.878],[-64.463,-349.256],[-87.246,-349.256]],"c":true},"ix":2},"nm":"Path 26","mn":"ADBE Vector Shape - Group","hd":true},{"ind":26,"ty":"sh","ix":27,"ks":{"a":0,"k":{"i":[[0,3.657],[-3.159,0],[0,0],[0,-3.656],[3.16,0],[0,0]],"o":[[0,-3.656],[0,0],[3.16,0],[0,3.657],[0,0],[-3.159,0]],"v":[[-100.715,355.878],[-94.994,349.257],[-72.211,349.257],[-66.489,355.878],[-72.211,362.5],[-94.994,362.5]],"c":true},"ix":2},"nm":"Path 27","mn":"ADBE Vector Shape - Group","hd":true},{"ind":27,"ty":"sh","ix":28,"ks":{"a":0,"k":{"i":[[0,3.657],[-3.159,0],[0,0],[0,-3.657],[3.159,0],[0,0]],"o":[[0,-3.657],[0,0],[3.159,0],[0,3.657],[0,0],[-3.159,0]],"v":[[-138.533,-355.878],[-132.812,-362.5],[-110.029,-362.5],[-104.308,-355.878],[-110.029,-349.256],[-132.812,-349.256]],"c":true},"ix":2},"nm":"Path 28","mn":"ADBE Vector Shape - Group","hd":true},{"ind":28,"ty":"sh","ix":29,"ks":{"a":0,"k":{"i":[[0,3.657],[-3.16,0],[0,0],[0,-3.656],[3.16,0],[0,0]],"o":[[0,-3.656],[0,0],[3.16,0],[0,3.657],[0,0],[-3.16,0]],"v":[[-146.281,355.878],[-140.559,349.257],[-117.777,349.257],[-112.056,355.878],[-117.777,362.5],[-140.559,362.5]],"c":true},"ix":2},"nm":"Path 29","mn":"ADBE Vector Shape - Group","hd":true},{"ind":29,"ty":"sh","ix":30,"ks":{"a":0,"k":{"i":[[0,3.657],[-3.16,0],[0,0],[0,-3.657],[3.16,0],[0,0]],"o":[[0,-3.657],[0,0],[3.16,0],[0,3.657],[0,0],[-3.16,0]],"v":[[-184.1,-355.878],[-178.378,-362.5],[-155.595,-362.5],[-149.874,-355.878],[-155.595,-349.256],[-178.378,-349.256]],"c":true},"ix":2},"nm":"Path 30","mn":"ADBE Vector Shape - Group","hd":true},{"ind":30,"ty":"sh","ix":31,"ks":{"a":0,"k":{"i":[[0,3.657],[-3.159,0],[0,0],[0,-3.656],[3.159,0],[0,0]],"o":[[0,-3.656],[0,0],[3.159,0],[0,3.657],[0,0],[-3.159,0]],"v":[[-191.847,355.878],[-186.126,349.257],[-163.342,349.257],[-157.621,355.878],[-163.342,362.5],[-186.126,362.5]],"c":true},"ix":2},"nm":"Path 31","mn":"ADBE Vector Shape - Group","hd":true},{"ind":31,"ty":"sh","ix":32,"ks":{"a":0,"k":{"i":[[0,3.657],[0,0],[-5.257,0],[0,0],[0,-3.657],[3.111,-0.065],[0,0],[3.159,0]],"o":[[0,0],[0,-6.086],[0,0],[3.159,0],[0,3.617],[0,0],[0,3.657],[-3.16,0]],"v":[[-212.499,-334.115],[-212.499,-351.463],[-202.964,-362.5],[-201.16,-362.5],[-195.439,-355.878],[-201.056,-349.257],[-201.056,-334.115],[-206.777,-327.493]],"c":true},"ix":2},"nm":"Path 32","mn":"ADBE Vector Shape - Group","hd":true},{"ind":32,"ty":"sh","ix":33,"ks":{"a":0,"k":{"i":[[0,3.657],[0,0],[-3.16,0],[0,-3.657],[0,0],[3.159,0]],"o":[[0,0],[0,-3.657],[3.159,0],[0,0],[0,3.657],[-3.16,0]],"v":[[-212.499,-281.377],[-212.499,-307.746],[-206.777,-314.368],[-201.056,-307.746],[-201.056,-281.377],[-206.777,-274.755]],"c":true},"ix":2},"nm":"Path 33","mn":"ADBE Vector Shape - Group","hd":true},{"ind":33,"ty":"sh","ix":34,"ks":{"a":0,"k":{"i":[[0,3.657],[0,0],[-3.16,0],[0,-3.657],[0,0],[3.159,0]],"o":[[0,0],[0,-3.657],[3.159,0],[0,0],[0,3.657],[-3.16,0]],"v":[[-212.499,-228.641],[-212.499,-255.009],[-206.777,-261.631],[-201.056,-255.009],[-201.056,-228.641],[-206.777,-222.019]],"c":true},"ix":2},"nm":"Path 34","mn":"ADBE Vector Shape - Group","hd":true},{"ind":34,"ty":"sh","ix":35,"ks":{"a":0,"k":{"i":[[0,3.657],[0,0],[-3.16,0],[0,-3.657],[0,0],[3.159,0]],"o":[[0,0],[0,-3.657],[3.159,0],[0,0],[0,3.657],[-3.16,0]],"v":[[-212.499,-175.904],[-212.499,-202.273],[-206.777,-208.895],[-201.056,-202.273],[-201.056,-175.904],[-206.777,-169.282]],"c":true},"ix":2},"nm":"Path 35","mn":"ADBE Vector Shape - Group","hd":true},{"ind":35,"ty":"sh","ix":36,"ks":{"a":0,"k":{"i":[[0,3.657],[0,0],[-3.16,0],[0,-3.657],[0,0],[3.159,0]],"o":[[0,0],[0,-3.657],[3.159,0],[0,0],[0,3.657],[-3.16,0]],"v":[[-212.499,-123.168],[-212.499,-149.535],[-206.777,-156.157],[-201.056,-149.535],[-201.056,-123.168],[-206.777,-116.546]],"c":true},"ix":2},"nm":"Path 36","mn":"ADBE Vector Shape - Group","hd":true},{"ind":36,"ty":"sh","ix":37,"ks":{"a":0,"k":{"i":[[0,3.656],[0,0],[-3.16,0],[0,-3.657],[0,0],[3.159,0]],"o":[[0,0],[0,-3.657],[3.159,0],[0,0],[0,3.656],[-3.16,0]],"v":[[-212.499,-70.43],[-212.499,-96.799],[-206.777,-103.421],[-201.056,-96.799],[-201.056,-70.43],[-206.777,-63.808]],"c":true},"ix":2},"nm":"Path 37","mn":"ADBE Vector Shape - Group","hd":true},{"ind":37,"ty":"sh","ix":38,"ks":{"a":0,"k":{"i":[[0,3.657],[0,0],[-3.16,0],[0,-3.656],[0,0],[3.159,0]],"o":[[0,0],[0,-3.656],[3.159,0],[0,0],[0,3.657],[-3.16,0]],"v":[[-212.499,-17.694],[-212.499,-44.063],[-206.777,-50.684],[-201.056,-44.063],[-201.056,-17.694],[-206.777,-11.072]],"c":true},"ix":2},"nm":"Path 38","mn":"ADBE Vector Shape - Group","hd":true},{"ind":38,"ty":"sh","ix":39,"ks":{"a":0,"k":{"i":[[0,3.656],[0,0],[-3.16,0],[0,-3.657],[0,0],[3.159,0]],"o":[[0,0],[0,-3.657],[3.159,0],[0,0],[0,3.656],[-3.16,0]],"v":[[-212.499,35.043],[-212.499,8.674],[-206.777,2.052],[-201.056,8.674],[-201.056,35.043],[-206.777,41.665]],"c":true},"ix":2},"nm":"Path 39","mn":"ADBE Vector Shape - Group","hd":true},{"ind":39,"ty":"sh","ix":40,"ks":{"a":0,"k":{"i":[[0,3.657],[0,0],[-3.16,0],[0,-3.656],[0,0],[3.159,0]],"o":[[0,0],[0,-3.656],[3.159,0],[0,0],[0,3.657],[-3.16,0]],"v":[[-212.499,87.779],[-212.499,61.411],[-206.777,54.79],[-201.056,61.411],[-201.056,87.779],[-206.777,94.401]],"c":true},"ix":2},"nm":"Path 40","mn":"ADBE Vector Shape - Group","hd":true},{"ind":40,"ty":"sh","ix":41,"ks":{"a":0,"k":{"i":[[0,3.657],[0,0],[-3.16,0],[0,-3.657],[0,0],[3.159,0]],"o":[[0,0],[0,-3.657],[3.159,0],[0,0],[0,3.657],[-3.16,0]],"v":[[-212.499,140.517],[-212.499,114.148],[-206.777,107.526],[-201.056,114.148],[-201.056,140.517],[-206.777,147.139]],"c":true},"ix":2},"nm":"Path 41","mn":"ADBE Vector Shape - Group","hd":true},{"ind":41,"ty":"sh","ix":42,"ks":{"a":0,"k":{"i":[[0,3.657],[0,0],[-3.16,0],[0,-3.658],[0,0],[3.159,0]],"o":[[0,0],[0,-3.658],[3.159,0],[0,0],[0,3.657],[-3.16,0]],"v":[[-212.499,193.253],[-212.499,166.885],[-206.777,160.263],[-201.056,166.885],[-201.056,193.253],[-206.777,199.875]],"c":true},"ix":2},"nm":"Path 42","mn":"ADBE Vector Shape - Group","hd":true},{"ind":42,"ty":"sh","ix":43,"ks":{"a":0,"k":{"i":[[0,3.657],[0,0],[-3.16,0],[0,-3.657],[0,0],[3.159,0]],"o":[[0,0],[0,-3.657],[3.159,0],[0,0],[0,3.657],[-3.16,0]],"v":[[-212.499,245.989],[-212.499,219.622],[-206.777,213],[-201.056,219.622],[-201.056,245.989],[-206.777,252.611]],"c":true},"ix":2},"nm":"Path 43","mn":"ADBE Vector Shape - Group","hd":true},{"ind":43,"ty":"sh","ix":44,"ks":{"a":0,"k":{"i":[[0,3.657],[0,0],[-3.16,0],[0,-3.657],[0,0],[3.159,0]],"o":[[0,0],[0,-3.657],[3.159,0],[0,0],[0,3.657],[-3.16,0]],"v":[[-212.499,298.727],[-212.499,272.358],[-206.777,265.736],[-201.056,272.358],[-201.056,298.727],[-206.777,305.349]],"c":true},"ix":2},"nm":"Path 44","mn":"ADBE Vector Shape - Group","hd":true},{"ind":44,"ty":"sh","ix":45,"ks":{"a":0,"k":{"i":[[0,3.656],[-0.001,0.04],[0,0],[-3.16,0],[0,-3.657],[0,0],[0.001,-0.053],[3.128,0.001]],"o":[[0,-0.037],[0,0],[0,-3.657],[3.159,0],[0,0],[0,0.053],[-0.051,3.607],[-3.16,0]],"v":[[-212.5,351.516],[-212.499,351.402],[-212.499,325.095],[-206.777,318.473],[-201.056,325.095],[-201.056,351.464],[-201.058,351.622],[-206.779,358.135]],"c":true},"ix":2},"nm":"Path 45","mn":"ADBE Vector Shape - Group","hd":true},{"ty":"mm","mm":1,"nm":"Merge Paths 1","mn":"ADBE Vector Filter - Merge","hd":true},{"ty":"fl","c":{"a":0,"k":[1,1,1,1],"ix":4},"o":{"a":1,"k":[{"i":{"x":[0.667],"y":[1]},"o":{"x":[0.333],"y":[0]},"n":["0p667_1_0p333_0"],"t":15,"s":[100],"e":[25]},{"t":30}],"ix":5},"r":1,"nm":"Fill 1","mn":"ADBE Vector Graphic - Fill","hd":true},{"ty":"tr","p":{"a":0,"k":[371.53,592.999],"ix":2},"a":{"a":0,"k":[0,0],"ix":1},"s":{"a":0,"k":[100,100],"ix":3},"r":{"a":0,"k":0,"ix":6},"o":{"a":0,"k":100,"ix":7},"sk":{"a":0,"k":0,"ix":4},"sa":{"a":0,"k":0,"ix":5},"nm":"Transform"}],"nm":"Group 1","np":47,"cix":2,"ix":1,"mn":"ADBE Vector Group","hd":true},{"ty":"gr","it":[{"ind":0,"ty":"sh","ix":1,"ks":{"a":0,"k":{"i":[[0,1.375],[0,0],[-1.375,0],[0,0],[0,-1.375],[0,0],[1.375,0],[0,0]],"o":[[0,0],[0,-1.375],[0,0],[1.375,0],[0,0],[0,1.375],[0,0],[-1.375,0]],"v":[[-8.384,5.884],[-8.384,-5.884],[-5.884,-8.384],[5.884,-8.384],[8.384,-5.884],[8.384,5.884],[5.884,8.384],[-5.884,8.384]],"c":true},"ix":2},"nm":"Path 1","mn":"ADBE Vector Shape - Group","hd":false},{"ty":"fl","c":{"a":0,"k":[0.2,0.2,0.2,1],"ix":4},"o":{"a":0,"k":100,"ix":5},"r":1,"nm":"Fill 1","mn":"ADBE Vector Graphic - Fill","hd":false},{"ty":"tr","p":{"a":0,"k":[299.424,150.049],"ix":2},"a":{"a":0,"k":[0,0],"ix":1},"s":{"a":0,"k":[100,100],"ix":3},"r":{"a":0,"k":0,"ix":6},"o":{"a":0,"k":100,"ix":7},"sk":{"a":0,"k":0,"ix":4},"sa":{"a":0,"k":0,"ix":5},"nm":"Transform"}],"nm":"Group 2","np":2,"cix":2,"ix":2,"mn":"ADBE Vector Group","hd":false},{"ty":"gr","it":[{"ind":0,"ty":"sh","ix":1,"ks":{"a":0,"k":{"i":[[0,1.375],[0,0],[-1.375,0],[0,0],[0,-1.375],[0,0],[1.375,0],[0,0]],"o":[[0,0],[0,-1.375],[0,0],[1.375,0],[0,0],[0,1.375],[0,0],[-1.375,0]],"v":[[-65.398,5.884],[-65.398,-5.884],[-62.898,-8.384],[62.898,-8.384],[65.398,-5.884],[65.398,5.884],[62.898,8.384],[-62.898,8.384]],"c":true},"ix":2},"nm":"Path 1","mn":"ADBE Vector Shape - Group","hd":false},{"ty":"fl","c":{"a":0,"k":[0.2,0.2,0.2,1],"ix":4},"o":{"a":0,"k":100,"ix":5},"r":1,"nm":"Fill 1","mn":"ADBE Vector Graphic - Fill","hd":false},{"ty":"tr","p":{"a":0,"k":[386.622,150.049],"ix":2},"a":{"a":0,"k":[0,0],"ix":1},"s":{"a":0,"k":[100,100],"ix":3},"r":{"a":0,"k":0,"ix":6},"o":{"a":0,"k":100,"ix":7},"sk":{"a":0,"k":0,"ix":4},"sa":{"a":0,"k":0,"ix":5},"nm":"Transform"}],"nm":"Group 3","np":2,"cix":2,"ix":3,"mn":"ADBE Vector Group","hd":false},{"ty":"gr","it":[{"ind":0,"ty":"sh","ix":1,"ks":{"a":0,"k":{"i":[[18.522,0],[0,18.522],[-18.522,0],[0,-18.523]],"o":[[-18.522,0],[0,-18.523],[18.522,0],[0,18.522]],"v":[[0,33.537],[-33.538,0],[0,-33.537],[33.538,0]],"c":true},"ix":2},"nm":"Path 1","mn":"ADBE Vector Shape - Group","hd":false},{"ty":"fl","c":{"a":0,"k":[0.2,0.2,0.2,1],"ix":4},"o":{"a":0,"k":100,"ix":5},"r":1,"nm":"Fill 1","mn":"ADBE Vector Graphic - Fill","hd":false},{"ty":"tr","p":{"a":0,"k":[371.53,1040.467],"ix":2},"a":{"a":0,"k":[0,0],"ix":1},"s":{"a":0,"k":[100,100],"ix":3},"r":{"a":0,"k":0,"ix":6},"o":{"a":0,"k":100,"ix":7},"sk":{"a":0,"k":0,"ix":4},"sa":{"a":0,"k":0,"ix":5},"nm":"Transform"}],"nm":"Group 4","np":2,"cix":2,"ix":4,"mn":"ADBE Vector Group","hd":false},{"ty":"gr","it":[{"ind":0,"ty":"sh","ix":1,"ks":{"a":0,"k":{"i":[[0,2.2],[0,0],[2.199,0],[0,0],[0,-2.201],[0,0],[-2.2,0],[0,0]],"o":[[0,0],[0,-2.201],[0,0],[-2.2,0],[0,0],[0,2.2],[0,0],[2.199,0]],"v":[[243.146,396.772],[243.146,-396.772],[239.146,-400.772],[-239.147,-400.772],[-243.147,-396.772],[-243.147,396.772],[-239.147,400.772],[239.146,400.772]],"c":true},"ix":2},"nm":"Path 1","mn":"ADBE Vector Shape - Group","hd":false},{"ind":1,"ty":"sh","ix":2,"ks":{"a":0,"k":{"i":[[0,0],[0,0],[0,0],[0,0]],"o":[[0,0],[0,0],[0,0],[0,0]],"v":[[237.146,394.772],[-237.147,394.772],[-237.147,-394.772],[237.146,-394.772]],"c":true},"ix":2},"nm":"Path 2","mn":"ADBE Vector Shape - Group","hd":false},{"ty":"mm","mm":1,"nm":"Merge Paths 1","mn":"ADBE Vector Filter - Merge","hd":false},{"ty":"fl","c":{"a":0,"k":[0.6,0.6,0.6,1],"ix":4},"o":{"a":0,"k":100,"ix":5},"r":1,"nm":"Fill 1","mn":"ADBE Vector Graphic - Fill","hd":false},{"ty":"tr","p":{"a":0,"k":[371.53,592.743],"ix":2},"a":{"a":0,"k":[0,0],"ix":1},"s":{"a":0,"k":[100,100],"ix":3},"r":{"a":0,"k":0,"ix":6},"o":{"a":0,"k":100,"ix":7},"sk":{"a":0,"k":0,"ix":4},"sa":{"a":0,"k":0,"ix":5},"nm":"Transform"}],"nm":"Group 5","np":4,"cix":2,"ix":5,"mn":"ADBE Vector Group","hd":false},{"ty":"gr","it":[{"ind":0,"ty":"sh","ix":1,"ks":{"a":0,"k":{"i":[[0,0],[2.2,0],[0,0],[0,2.2],[0,0],[-2.2,0],[0,0],[0,-2.2]],"o":[[0,2.2],[0,0],[-2.2,0],[0,0],[0,-2.2],[0,0],[2.2,0],[0,0]],"v":[[243.146,390.065],[239.146,394.065],[-239.146,394.065],[-243.146,390.065],[-243.146,-403.479],[-239.146,-407.479],[239.146,-407.479],[243.146,-403.479]],"c":true},"ix":2},"nm":"Path 1","mn":"ADBE Vector Shape - Group","hd":false},{"ind":1,"ty":"sh","ix":2,"ks":{"a":0,"k":{"i":[[6.6,0],[0,0],[0,-6.6],[0,0],[-6.6,0],[0,0],[0,6.6],[0,0]],"o":[[0,0],[-6.6,0],[0,0],[0,6.6],[0,0],[6.6,0],[0,0],[0,-6.6]],"v":[[261.33,-493],[-261.33,-493],[-273.33,-481],[-273.33,481],[-261.33,493],[261.33,493],[273.33,481],[273.33,-481]],"c":true},"ix":2},"nm":"Path 2","mn":"ADBE Vector Shape - Group","hd":false},{"ty":"mm","mm":1,"nm":"Merge Paths 1","mn":"ADBE Vector Filter - Merge","hd":false},{"ty":"fl","c":{"a":0,"k":[0,0,0,1],"ix":4},"o":{"a":0,"k":100,"ix":5},"r":1,"nm":"Fill 1","mn":"ADBE Vector Graphic - Fill","hd":false},{"ty":"tr","p":{"a":0,"k":[371.53,599.45],"ix":2},"a":{"a":0,"k":[0,0],"ix":1},"s":{"a":0,"k":[100,100],"ix":3},"r":{"a":0,"k":0,"ix":6},"o":{"a":0,"k":100,"ix":7},"sk":{"a":0,"k":0,"ix":4},"sa":{"a":0,"k":0,"ix":5},"nm":"Transform"}],"nm":"Group 6","np":4,"cix":2,"ix":6,"mn":"ADBE Vector Group","hd":false},{"ty":"gr","it":[{"ind":0,"ty":"sh","ix":1,"ks":{"a":0,"k":{"i":[[0.774,3.769],[-0.126,0.225],[-0.646,0.62],[-4.513,34.013],[4.242,-13.738],[-5.645,0],[0,-3.956],[14.567,0]],"o":[[-0.145,-0.052],[0,-0.677],[5.008,-10.602],[4.948,0.336],[4.289,-0.819],[14.567,0],[0,3.959],[-14.068,0]],"v":[[-26.274,35.57],[-26.317,35.164],[-25.324,33.211],[-5.95,-42.329],[-15.097,29.299],[0.064,27.999],[26.443,35.164],[0.064,42.329]],"c":true},"ix":2},"nm":"Path 1","mn":"ADBE Vector Shape - Group","hd":false},{"ty":"fl","c":{"a":0,"k":[0.827000038297,0.57599995931,0.442999985639,1],"ix":4},"o":{"a":0,"k":100,"ix":5},"r":1,"nm":"Fill 1","mn":"ADBE Vector Graphic - Fill","hd":false},{"ty":"tr","p":{"a":1,"k":[{"i":{"x":0.833,"y":1},"o":{"x":0.333,"y":0},"n":"0p833_1_0p333_0","t":0,"s":[346.739,689.33],"e":[378.739,657.33],"to":[5.33333349227905,-5.33333349227905],"ti":[-5.33333349227905,5.33333349227905]},{"i":{"x":0.833,"y":0.833},"o":{"x":0.333,"y":0.333},"n":"0p833_0p833_0p333_0p333","t":30,"s":[378.739,657.33],"e":[378.739,657.33],"to":[0,0],"ti":[0,0]},{"i":{"x":0.667,"y":1},"o":{"x":0.333,"y":0},"n":"0p667_1_0p333_0","t":62,"s":[378.739,657.33],"e":[368.739,657.33],"to":[-1.66666662693024,0],"ti":[1.66666662693024,0]},{"i":{"x":0.667,"y":0.667},"o":{"x":0.167,"y":0.167},"n":"0p667_0p667_0p167_0p167","t":77,"s":[368.739,657.33],"e":[368.739,657.33],"to":[0,0],"ti":[0,0]},{"i":{"x":0.667,"y":1},"o":{"x":0.167,"y":0},"n":"0p667_1_0p167_0","t":157,"s":[368.739,657.33],"e":[373.739,657.33],"to":[0.83333331346512,0],"ti":[-0.83333331346512,0]},{"i":{"x":0.667,"y":0.667},"o":{"x":0.167,"y":0.167},"n":"0p667_0p667_0p167_0p167","t":169,"s":[373.739,657.33],"e":[373.739,657.33],"to":[0,0],"ti":[0,0]},{"i":{"x":0.667,"y":1},"o":{"x":0.167,"y":0},"n":"0p667_1_0p167_0","t":264,"s":[373.739,657.33],"e":[382.739,654.33],"to":[1.5,-0.5],"ti":[-1.5,0.5]},{"t":277}],"ix":2},"a":{"a":0,"k":[0,0],"ix":1},"s":{"a":0,"k":[100,100],"ix":3},"r":{"a":1,"k":[{"i":{"x":[0.667],"y":[1]},"o":{"x":[0.333],"y":[0]},"n":["0p667_1_0p333_0"],"t":62,"s":[-1],"e":[-1]},{"i":{"x":[0.833],"y":[1]},"o":{"x":[0.167],"y":[0]},"n":["0p833_1_0p167_0"],"t":77,"s":[-1],"e":[-1]},{"i":{"x":[0.833],"y":[1]},"o":{"x":[0.167],"y":[0]},"n":["0p833_1_0p167_0"],"t":157,"s":[-1],"e":[-1]},{"i":{"x":[0.833],"y":[1]},"o":{"x":[0.167],"y":[0]},"n":["0p833_1_0p167_0"],"t":169,"s":[-1],"e":[-1]},{"i":{"x":[0.833],"y":[1]},"o":{"x":[0.167],"y":[0]},"n":["0p833_1_0p167_0"],"t":264,"s":[-1],"e":[-2]},{"t":277}],"ix":6},"o":{"a":0,"k":100,"ix":7},"sk":{"a":1,"k":[{"i":{"x":[0.667],"y":[1]},"o":{"x":[0.333],"y":[0]},"n":["0p667_1_0p333_0"],"t":62,"s":[0],"e":[5]},{"i":{"x":[0.833],"y":[1]},"o":{"x":[0.167],"y":[0]},"n":["0p833_1_0p167_0"],"t":77,"s":[5],"e":[5]},{"i":{"x":[0.833],"y":[1]},"o":{"x":[0.167],"y":[0]},"n":["0p833_1_0p167_0"],"t":157,"s":[5],"e":[3]},{"i":{"x":[0.833],"y":[1]},"o":{"x":[0.167],"y":[0]},"n":["0p833_1_0p167_0"],"t":169,"s":[3],"e":[3]},{"i":{"x":[0.833],"y":[1]},"o":{"x":[0.167],"y":[0]},"n":["0p833_1_0p167_0"],"t":264,"s":[3],"e":[1]},{"t":277}],"ix":4},"sa":{"a":0,"k":0,"ix":5},"nm":"Transform"}],"nm":"Group 8","np":2,"cix":2,"ix":7,"mn":"ADBE Vector Group","hd":false},{"ty":"gr","it":[{"ind":0,"ty":"sh","ix":1,"ks":{"a":0,"k":{"i":[[-22.375,32.851],[7.445,46.062]],"o":[[-7.445,46.062],[22.376,32.851]],"v":[[41.198,-23.031],[-41.198,-23.031]],"c":true},"ix":2},"nm":"Path 1","mn":"ADBE Vector Shape - Group","hd":false},{"ty":"fl","c":{"a":0,"k":[0.838999968884,0.510000011968,0.356999984442,1],"ix":4},"o":{"a":0,"k":100,"ix":5},"r":1,"nm":"Fill 1","mn":"ADBE Vector Graphic - Fill","hd":false},{"ty":"tr","p":{"a":1,"k":[{"i":{"x":0.833,"y":1},"o":{"x":0.333,"y":0},"n":"0p833_1_0p333_0","t":0,"s":[347.987,771.789],"e":[379.987,739.789],"to":[5.33333349227905,-5.33333349227905],"ti":[-5.33333349227905,5.33333349227905]},{"i":{"x":0.833,"y":0.833},"o":{"x":0.333,"y":0.333},"n":"0p833_0p833_0p333_0p333","t":30,"s":[379.987,739.789],"e":[379.987,739.789],"to":[0,0],"ti":[0,0]},{"i":{"x":0.667,"y":1},"o":{"x":0.333,"y":0},"n":"0p667_1_0p333_0","t":62,"s":[379.987,739.789],"e":[369.987,739.789],"to":[-1.66666662693024,0],"ti":[1.66666662693024,0]},{"i":{"x":0.667,"y":0.667},"o":{"x":0.167,"y":0.167},"n":"0p667_0p667_0p167_0p167","t":77,"s":[369.987,739.789],"e":[369.987,739.789],"to":[0,0],"ti":[0,0]},{"i":{"x":0.667,"y":1},"o":{"x":0.167,"y":0},"n":"0p667_1_0p167_0","t":157,"s":[369.987,739.789],"e":[373.987,739.789],"to":[0.66666668653488,0],"ti":[-0.66666668653488,0]},{"i":{"x":0.667,"y":0.667},"o":{"x":0.167,"y":0.167},"n":"0p667_0p667_0p167_0p167","t":169,"s":[373.987,739.789],"e":[373.987,739.789],"to":[0,0],"ti":[0,0]},{"i":{"x":0.667,"y":1},"o":{"x":0.167,"y":0},"n":"0p667_1_0p167_0","t":264,"s":[373.987,739.789],"e":[385.987,738.789],"to":[2,-0.16666667163372],"ti":[-2,0.16666667163372]},{"t":277}],"ix":2},"a":{"a":0,"k":[0,0],"ix":1},"s":{"a":0,"k":[100,100],"ix":3},"r":{"a":1,"k":[{"i":{"x":[0.667],"y":[1]},"o":{"x":[0.333],"y":[0]},"n":["0p667_1_0p333_0"],"t":62,"s":[0],"e":[3]},{"i":{"x":[0.833],"y":[1]},"o":{"x":[0.167],"y":[0]},"n":["0p833_1_0p167_0"],"t":77,"s":[3],"e":[3]},{"i":{"x":[0.833],"y":[1]},"o":{"x":[0.167],"y":[0]},"n":["0p833_1_0p167_0"],"t":264,"s":[3],"e":[-4]},{"t":277}],"ix":6},"o":{"a":0,"k":100,"ix":7},"sk":{"a":1,"k":[{"i":{"x":[0.667],"y":[1]},"o":{"x":[0.333],"y":[0]},"n":["0p667_1_0p333_0"],"t":62,"s":[0],"e":[5]},{"i":{"x":[0.833],"y":[1]},"o":{"x":[0.167],"y":[0]},"n":["0p833_1_0p167_0"],"t":77,"s":[5],"e":[5]},{"i":{"x":[0.833],"y":[1]},"o":{"x":[0.167],"y":[0]},"n":["0p833_1_0p167_0"],"t":264,"s":[5],"e":[-4.5]},{"t":277}],"ix":4},"sa":{"a":0,"k":0,"ix":5},"nm":"Transform"}],"nm":"Group 9","np":2,"cix":2,"ix":8,"mn":"ADBE Vector Group","hd":false},{"ty":"gr","it":[{"ind":0,"ty":"sh","ix":1,"ks":{"a":0,"k":{"i":[[-1.195,2.15],[21.421,0.295],[-17.275,0.446]],"o":[[4.075,-7.339],[-35.925,-0.498],[12.908,-0.339]],"v":[[44.906,2.651],[6.504,-8.945],[-31.707,8.997]],"c":true},"ix":2},"nm":"Path 1","mn":"ADBE Vector Shape - Group","hd":false},{"ty":"fl","c":{"a":0,"k":[0,0,0,1],"ix":4},"o":{"a":0,"k":100,"ix":5},"r":1,"nm":"Fill 1","mn":"ADBE Vector Graphic - Fill","hd":false},{"ty":"tr","p":{"a":1,"k":[{"i":{"x":0.833,"y":1},"o":{"x":0.333,"y":0},"n":"0p833_1_0p333_0","t":0,"s":[416.377,614.886],"e":[448.377,582.886],"to":[5.33333349227905,-5.33333349227905],"ti":[-5.33333349227905,5.33333349227905]},{"i":{"x":0.833,"y":0.833},"o":{"x":0.333,"y":0.333},"n":"0p833_0p833_0p333_0p333","t":30,"s":[448.377,582.886],"e":[448.377,582.886],"to":[0,0],"ti":[0,0]},{"i":{"x":0.667,"y":1},"o":{"x":0.333,"y":0},"n":"0p667_1_0p333_0","t":62,"s":[448.377,582.886],"e":[442.377,576.886],"to":[-1,-1],"ti":[1,1]},{"i":{"x":0.667,"y":0.667},"o":{"x":0.167,"y":0.167},"n":"0p667_0p667_0p167_0p167","t":77,"s":[442.377,576.886],"e":[442.377,576.886],"to":[0,0],"ti":[0,0]},{"i":{"x":0.667,"y":1},"o":{"x":0.167,"y":0},"n":"0p667_1_0p167_0","t":157,"s":[442.377,576.886],"e":[441.377,583.886],"to":[-0.16666667163372,1.16666662693024],"ti":[0.16666667163372,-1.16666662693024]},{"i":{"x":0.667,"y":0.667},"o":{"x":0.167,"y":0.167},"n":"0p667_0p667_0p167_0p167","t":169,"s":[441.377,583.886],"e":[441.377,583.886],"to":[0,0],"ti":[0,0]},{"i":{"x":0.667,"y":1},"o":{"x":0.167,"y":0},"n":"0p667_1_0p167_0","t":264,"s":[441.377,583.886],"e":[457.377,578.886],"to":[2.66666674613953,-0.83333331346512],"ti":[-2.66666674613953,0.83333331346512]},{"t":277}],"ix":2},"a":{"a":0,"k":[0,0],"ix":1},"s":{"a":0,"k":[100,100],"ix":3},"r":{"a":1,"k":[{"i":{"x":[0.667],"y":[1]},"o":{"x":[0.333],"y":[0]},"n":["0p667_1_0p333_0"],"t":264,"s":[0],"e":[-4]},{"t":277}],"ix":6},"o":{"a":0,"k":100,"ix":7},"sk":{"a":1,"k":[{"i":{"x":[0.667],"y":[1]},"o":{"x":[0.333],"y":[0]},"n":["0p667_1_0p333_0"],"t":62,"s":[0],"e":[5]},{"i":{"x":[0.833],"y":[1]},"o":{"x":[0.167],"y":[0]},"n":["0p833_1_0p167_0"],"t":77,"s":[5],"e":[5]},{"i":{"x":[0.833],"y":[1]},"o":{"x":[0.167],"y":[0]},"n":["0p833_1_0p167_0"],"t":157,"s":[5],"e":[0]},{"i":{"x":[0.833],"y":[1]},"o":{"x":[0.167],"y":[0]},"n":["0p833_1_0p167_0"],"t":169,"s":[0],"e":[0]},{"i":{"x":[0.833],"y":[1]},"o":{"x":[0.167],"y":[0]},"n":["0p833_1_0p167_0"],"t":264,"s":[0],"e":[4]},{"t":277}],"ix":4},"sa":{"a":0,"k":0,"ix":5},"nm":"Transform"}],"nm":"Group 10","np":2,"cix":2,"ix":9,"mn":"ADBE Vector Group","hd":false},{"ty":"gr","it":[{"ind":0,"ty":"sh","ix":1,"ks":{"a":0,"k":{"i":[[1.154,2.175],[-21.421,-0.172],[17.265,0.827]],"o":[[-3.944,-7.427],[35.926,0.286],[-12.898,-0.617]],"v":[[-44.901,1.046],[-6.3,-9.713],[31.58,9.058]],"c":true},"ix":2},"nm":"Path 1","mn":"ADBE Vector Shape - Group","hd":false},{"ty":"fl","c":{"a":0,"k":[0,0,0,1],"ix":4},"o":{"a":0,"k":100,"ix":5},"r":1,"nm":"Fill 1","mn":"ADBE Vector Graphic - Fill","hd":false},{"ty":"tr","p":{"a":1,"k":[{"i":{"x":0.833,"y":1},"o":{"x":0.333,"y":0},"n":"0p833_1_0p333_0","t":0,"s":[269.424,614.806],"e":[301.424,582.806],"to":[5.33333349227905,-5.33333349227905],"ti":[-5.33333349227905,5.33333349227905]},{"i":{"x":0.833,"y":0.833},"o":{"x":0.333,"y":0.333},"n":"0p833_0p833_0p333_0p333","t":30,"s":[301.424,582.806],"e":[301.424,582.806],"to":[0,0],"ti":[0,0]},{"i":{"x":0.667,"y":1},"o":{"x":0.333,"y":0},"n":"0p667_1_0p333_0","t":62,"s":[301.424,582.806],"e":[295.424,576.806],"to":[-1,-1],"ti":[1,1]},{"i":{"x":0.667,"y":0.667},"o":{"x":0.167,"y":0.167},"n":"0p667_0p667_0p167_0p167","t":77,"s":[295.424,576.806],"e":[295.424,576.806],"to":[0,0],"ti":[0,0]},{"i":{"x":0.667,"y":1},"o":{"x":0.167,"y":0},"n":"0p667_1_0p167_0","t":157,"s":[295.424,576.806],"e":[294.424,583.806],"to":[-0.16666667163372,1.16666662693024],"ti":[0.16666667163372,-1.16666662693024]},{"i":{"x":0.667,"y":0.667},"o":{"x":0.167,"y":0.167},"n":"0p667_0p667_0p167_0p167","t":169,"s":[294.424,583.806],"e":[294.424,583.806],"to":[0,0],"ti":[0,0]},{"i":{"x":0.667,"y":1},"o":{"x":0.167,"y":0},"n":"0p667_1_0p167_0","t":264,"s":[294.424,583.806],"e":[310.424,578.806],"to":[2.66666674613953,-0.83333331346512],"ti":[-2.66666674613953,0.83333331346512]},{"t":277}],"ix":2},"a":{"a":0,"k":[0,0],"ix":1},"s":{"a":0,"k":[100,100],"ix":3},"r":{"a":1,"k":[{"i":{"x":[0.667],"y":[1]},"o":{"x":[0.333],"y":[0]},"n":["0p667_1_0p333_0"],"t":264,"s":[0],"e":[-4]},{"t":277}],"ix":6},"o":{"a":0,"k":100,"ix":7},"sk":{"a":1,"k":[{"i":{"x":[0.667],"y":[1]},"o":{"x":[0.333],"y":[0]},"n":["0p667_1_0p333_0"],"t":62,"s":[0],"e":[5]},{"i":{"x":[0.833],"y":[1]},"o":{"x":[0.167],"y":[0]},"n":["0p833_1_0p167_0"],"t":77,"s":[5],"e":[5]},{"i":{"x":[0.833],"y":[1]},"o":{"x":[0.167],"y":[0]},"n":["0p833_1_0p167_0"],"t":157,"s":[5],"e":[0]},{"i":{"x":[0.833],"y":[1]},"o":{"x":[0.167],"y":[0]},"n":["0p833_1_0p167_0"],"t":169,"s":[0],"e":[0]},{"i":{"x":[0.833],"y":[1]},"o":{"x":[0.167],"y":[0]},"n":["0p833_1_0p167_0"],"t":264,"s":[0],"e":[4]},{"t":277}],"ix":4},"sa":{"a":0,"k":0,"ix":5},"nm":"Transform"}],"nm":"Group 11","np":2,"cix":2,"ix":10,"mn":"ADBE Vector Group","hd":false},{"ty":"gr","it":[{"ind":0,"ty":"sh","ix":1,"ks":{"a":0,"k":{"i":[[-6.714,0],[0,7.385],[6.715,0],[0,-7.383]],"o":[[6.715,0],[0,-7.383],[-6.714,0],[0,7.385]],"v":[[0,13.406],[12.19,0],[0,-13.406],[-12.19,0]],"c":true},"ix":2},"nm":"Path 1","mn":"ADBE Vector Shape - Group","hd":false},{"ty":"fl","c":{"a":0,"k":[0.243000000598,0.231000010173,0.226999993418,1],"ix":4},"o":{"a":0,"k":100,"ix":5},"r":1,"nm":"Fill 1","mn":"ADBE Vector Graphic - Fill","hd":false},{"ty":"tr","p":{"a":1,"k":[{"i":{"x":0.833,"y":1},"o":{"x":0.333,"y":0},"n":"0p833_1_0p333_0","t":0,"s":[422.588,657.435],"e":[454.588,625.435],"to":[5.33333349227905,-5.33333349227905],"ti":[-5.33333349227905,5.33333349227905]},{"i":{"x":0.833,"y":0.833},"o":{"x":0.333,"y":0.333},"n":"0p833_0p833_0p333_0p333","t":30,"s":[454.588,625.435],"e":[454.588,625.435],"to":[0,0],"ti":[0,0]},{"i":{"x":0.667,"y":1},"o":{"x":0.333,"y":0},"n":"0p667_1_0p333_0","t":62,"s":[454.588,625.435],"e":[444.588,615.435],"to":[-1.66666662693024,-1.66666662693024],"ti":[1.66666662693024,1.66666662693024]},{"i":{"x":0.667,"y":0.667},"o":{"x":0.167,"y":0.167},"n":"0p667_0p667_0p167_0p167","t":77,"s":[444.588,615.435],"e":[444.588,615.435],"to":[0,0],"ti":[0,0]},{"i":{"x":0.667,"y":1},"o":{"x":0.167,"y":0},"n":"0p667_1_0p167_0","t":157,"s":[444.588,615.435],"e":[442.588,625.435],"to":[-0.33333334326744,1.66666662693024],"ti":[0.33333334326744,-1.66666662693024]},{"i":{"x":0.667,"y":0.667},"o":{"x":0.167,"y":0.167},"n":"0p667_0p667_0p167_0p167","t":169,"s":[442.588,625.435],"e":[442.588,625.435],"to":[0,0],"ti":[0,0]},{"i":{"x":0.667,"y":1},"o":{"x":0.167,"y":0},"n":"0p667_1_0p167_0","t":264,"s":[442.588,625.435],"e":[466.588,622.435],"to":[4,-0.5],"ti":[-4,0.5]},{"t":277}],"ix":2},"a":{"a":0,"k":[0,0],"ix":1},"s":{"a":0,"k":[100,100],"ix":3},"r":{"a":0,"k":0,"ix":6},"o":{"a":0,"k":100,"ix":7},"sk":{"a":0,"k":0,"ix":4},"sa":{"a":0,"k":0,"ix":5},"nm":"Transform"}],"nm":"Group 12","np":2,"cix":2,"ix":11,"mn":"ADBE Vector Group","hd":false},{"ty":"gr","it":[{"ind":0,"ty":"sh","ix":1,"ks":{"a":0,"k":{"i":[[-6.716,0],[0,7.385],[6.716,0],[0,-7.387]],"o":[[6.716,0],[0,-7.387],[-6.716,0],[0,7.385]],"v":[[-0.001,13.407],[12.192,0.002],[-0.001,-13.407],[-12.192,0.002]],"c":true},"ix":2},"nm":"Path 1","mn":"ADBE Vector Shape - Group","hd":false},{"ty":"fl","c":{"a":0,"k":[0.243000000598,0.231000010173,0.226999993418,1],"ix":4},"o":{"a":0,"k":100,"ix":5},"r":1,"nm":"Fill 1","mn":"ADBE Vector Graphic - Fill","hd":false},{"ty":"tr","p":{"a":1,"k":[{"i":{"x":0.833,"y":1},"o":{"x":0.333,"y":0},"n":"0p833_1_0p333_0","t":0,"s":[263.252,657.434],"e":[295.252,625.434],"to":[5.33333349227905,-5.33333349227905],"ti":[-5.33333349227905,5.33333349227905]},{"i":{"x":0.833,"y":0.833},"o":{"x":0.333,"y":0.333},"n":"0p833_0p833_0p333_0p333","t":30,"s":[295.252,625.434],"e":[295.252,625.434],"to":[0,0],"ti":[0,0]},{"i":{"x":0.667,"y":1},"o":{"x":0.333,"y":0},"n":"0p667_1_0p333_0","t":62,"s":[295.252,625.434],"e":[285.252,615.434],"to":[-1.66666662693024,-1.66666662693024],"ti":[1.66666662693024,1.66666662693024]},{"i":{"x":0.667,"y":0.667},"o":{"x":0.167,"y":0.167},"n":"0p667_0p667_0p167_0p167","t":77,"s":[285.252,615.434],"e":[285.252,615.434],"to":[0,0],"ti":[0,0]},{"i":{"x":0.667,"y":1},"o":{"x":0.167,"y":0},"n":"0p667_1_0p167_0","t":157,"s":[285.252,615.434],"e":[283.252,625.434],"to":[-0.33333334326744,1.66666662693024],"ti":[0.33333334326744,-1.66666662693024]},{"i":{"x":0.667,"y":0.667},"o":{"x":0.167,"y":0.167},"n":"0p667_0p667_0p167_0p167","t":169,"s":[283.252,625.434],"e":[283.252,625.434],"to":[0,0],"ti":[0,0]},{"i":{"x":0.667,"y":1},"o":{"x":0.167,"y":0},"n":"0p667_1_0p167_0","t":264,"s":[283.252,625.434],"e":[307.252,622.434],"to":[4,-0.5],"ti":[-4,0.5]},{"t":277}],"ix":2},"a":{"a":0,"k":[0,0],"ix":1},"s":{"a":0,"k":[100,100],"ix":3},"r":{"a":0,"k":0,"ix":6},"o":{"a":0,"k":100,"ix":7},"sk":{"a":0,"k":0,"ix":4},"sa":{"a":0,"k":0,"ix":5},"nm":"Transform"}],"nm":"Group 13","np":2,"cix":2,"ix":12,"mn":"ADBE Vector Group","hd":false},{"ty":"gr","it":[{"ind":0,"ty":"sh","ix":1,"ks":{"a":0,"k":{"i":[[-8.349,-43.75],[5.369,51.824],[6.708,1.041],[0,0],[55.024,14.929],[42.494,25.64],[0,0],[4.025,-23.241],[0,0],[-12.746,16.212],[-164.045,68.375]],"o":[[0,-4.565],[-5.368,-51.821],[-6.71,-1.04],[0,0],[-55.023,-14.93],[-20.415,23.645],[0,0],[-4.025,23.239],[0,0],[0,0],[33.274,-13.867]],"v":[[151.755,144.68],[168.76,-33.531],[125.816,-88.839],[115.75,-92.031],[33.214,-130.723],[-142.118,-126.044],[-150.646,-56.622],[-170.104,-27.102],[-154.429,145.653],[-133.199,14.161],[121.617,-35.943]],"c":true},"ix":2},"nm":"Path 1","mn":"ADBE Vector Shape - Group","hd":false},{"ty":"fl","c":{"a":0,"k":[0,0,0,1],"ix":4},"o":{"a":0,"k":100,"ix":5},"r":1,"nm":"Fill 1","mn":"ADBE Vector Graphic - Fill","hd":false},{"ty":"tr","p":{"a":1,"k":[{"i":{"x":0.833,"y":1},"o":{"x":0.333,"y":0},"n":"0p833_1_0p333_0","t":0,"s":[343.85,508.363],"e":[375.85,476.363],"to":[5.33333349227905,-5.33333349227905],"ti":[-5.33333349227905,5.33333349227905]},{"i":{"x":0.833,"y":0.833},"o":{"x":0.333,"y":0.333},"n":"0p833_0p833_0p333_0p333","t":30,"s":[375.85,476.363],"e":[375.85,476.363],"to":[0,0],"ti":[0,0]},{"i":{"x":0.667,"y":1},"o":{"x":0.333,"y":0},"n":"0p667_1_0p333_0","t":62,"s":[375.85,476.363],"e":[377.85,473.363],"to":[0.33333334326744,-0.5],"ti":[-0.33333334326744,0.5]},{"i":{"x":0.667,"y":0.667},"o":{"x":0.167,"y":0.167},"n":"0p667_0p667_0p167_0p167","t":77,"s":[377.85,473.363],"e":[377.85,473.363],"to":[0,0],"ti":[0,0]},{"i":{"x":0.667,"y":1},"o":{"x":0.167,"y":0},"n":"0p667_1_0p167_0","t":157,"s":[377.85,473.363],"e":[375.85,476.363],"to":[-0.33332926034927,0.49999943375587],"ti":[0.33332926034927,-0.49999943375587]},{"i":{"x":0.667,"y":0.667},"o":{"x":0.167,"y":0.167},"n":"0p667_0p667_0p167_0p167","t":169,"s":[375.85,476.363],"e":[375.85,476.363],"to":[0,0],"ti":[0,0]},{"i":{"x":0.667,"y":1},"o":{"x":0.167,"y":0},"n":"0p667_1_0p167_0","t":264,"s":[375.85,476.363],"e":[375.35,480.363],"to":[-0.08333333581686,0.66666668653488],"ti":[0.08333333581686,-0.66666668653488]},{"t":277}],"ix":2},"a":{"a":0,"k":[0,0],"ix":1},"s":{"a":0,"k":[100,100],"ix":3},"r":{"a":1,"k":[{"i":{"x":[0.667],"y":[1]},"o":{"x":[0.333],"y":[0]},"n":["0p667_1_0p333_0"],"t":62,"s":[0],"e":[2]},{"i":{"x":[0.75],"y":[1.484]},"o":{"x":[0.16],"y":[0]},"n":["0p75_1p484_0p16_0"],"t":77,"s":[2],"e":[2]},{"i":{"x":[0.742],"y":[1]},"o":{"x":[0.403],"y":[0.059]},"n":["0p742_1_0p403_0p059"],"t":157,"s":[2],"e":[0]},{"i":{"x":[0.833],"y":[1]},"o":{"x":[0.167],"y":[0]},"n":["0p833_1_0p167_0"],"t":169,"s":[0],"e":[0]},{"i":{"x":[0.833],"y":[1]},"o":{"x":[0.167],"y":[0]},"n":["0p833_1_0p167_0"],"t":264,"s":[0],"e":[-2.5]},{"t":277}],"ix":6},"o":{"a":0,"k":100,"ix":7},"sk":{"a":0,"k":0,"ix":4},"sa":{"a":0,"k":0,"ix":5},"nm":"Transform"}],"nm":"Group 14","np":2,"cix":2,"ix":13,"mn":"ADBE Vector Group","hd":false},{"ty":"gr","it":[{"ind":0,"ty":"sh","ix":1,"ks":{"a":0,"k":{"i":[[25.441,38.017],[42.091,1.839],[1.357,0.059],[0,0],[10.537,-0.465],[0,0],[0,0],[0,0],[25.419,-37.979],[-2.003,-45.849],[-142.562,-1.31],[-5.15,116.979]],"o":[[-25.42,-37.979],[-0.008,0],[0,0],[0,0],[-10.537,-0.465],[0,0],[-1.353,0.059],[-42.097,1.839],[-25.442,38.017],[5.157,117.814],[142.991,1.318],[1.999,-45.849]],"v":[[130.03,-158.738],[22.876,-223.496],[20.691,-223.594],[20.741,-225.404],[0.003,-224.495],[-20.737,-225.404],[-20.694,-223.594],[-22.868,-223.496],[-130.023,-158.738],[-156.842,-26.991],[0.457,224.085],[156.846,-26.991]],"c":true},"ix":2},"nm":"Path 1","mn":"ADBE Vector Shape - Group","hd":false},{"ty":"fl","c":{"a":0,"k":[0.889999988032,0.638999968884,0.486000001197,1],"ix":4},"o":{"a":0,"k":100,"ix":5},"r":1,"nm":"Fill 1","mn":"ADBE Vector Graphic - Fill","hd":false},{"ty":"tr","p":{"a":1,"k":[{"i":{"x":0.667,"y":1},"o":{"x":0.333,"y":0},"n":"0p667_1_0p333_0","t":0,"s":[342.918,616.162],"e":[374.918,584.162],"to":[5.33333349227905,-5.33333349227905],"ti":[-5.5,5.33333349227905]},{"i":{"x":0.667,"y":1},"o":{"x":0.333,"y":0},"n":"0p667_1_0p333_0","t":30,"s":[374.918,584.162],"e":[375.918,584.162],"to":[5.5,-5.33333349227905],"ti":[-0.16666667163372,0]},{"t":277}],"ix":2},"a":{"a":0,"k":[0,0],"ix":1},"s":{"a":0,"k":[100,100],"ix":3},"r":{"a":1,"k":[{"i":{"x":[0.667],"y":[1]},"o":{"x":[0.333],"y":[0]},"n":["0p667_1_0p333_0"],"t":62,"s":[0],"e":[3]},{"i":{"x":[0.833],"y":[1]},"o":{"x":[0.167],"y":[0]},"n":["0p833_1_0p167_0"],"t":77,"s":[3],"e":[3]},{"i":{"x":[0.833],"y":[1]},"o":{"x":[0.167],"y":[0]},"n":["0p833_1_0p167_0"],"t":157,"s":[3],"e":[-1]},{"i":{"x":[0.833],"y":[1]},"o":{"x":[0.167],"y":[0]},"n":["0p833_1_0p167_0"],"t":169,"s":[-1],"e":[-1]},{"i":{"x":[0.833],"y":[1]},"o":{"x":[0.167],"y":[0]},"n":["0p833_1_0p167_0"],"t":264,"s":[-1],"e":[-5.5]},{"t":277}],"ix":6},"o":{"a":0,"k":100,"ix":7},"sk":{"a":0,"k":0,"ix":4},"sa":{"a":0,"k":0,"ix":5},"nm":"Transform"}],"nm":"Group 15","np":2,"cix":2,"ix":14,"mn":"ADBE Vector Group","hd":false},{"ty":"gr","it":[{"ind":0,"ty":"sh","ix":1,"ks":{"a":0,"k":{"i":[[-5.041,-28.911],[26.042,-5.185],[5.04,28.9],[-26.035,5.181]],"o":[[5.045,28.896],[-26.037,5.179],[-5.047,-28.897],[26.034,-5.187]],"v":[[47.133,-7.596],[9.132,50.552],[-47.13,11.171],[-9.132,-50.543]],"c":true},"ix":2},"nm":"Path 1","mn":"ADBE Vector Shape - Group","hd":false},{"ty":"fl","c":{"a":0,"k":[0.827000038297,0.57599995931,0.442999985639,1],"ix":4},"o":{"a":0,"k":100,"ix":5},"r":1,"nm":"Fill 1","mn":"ADBE Vector Graphic - Fill","hd":false},{"ty":"tr","p":{"a":1,"k":[{"i":{"x":0.833,"y":1},"o":{"x":0.333,"y":0},"n":"0p833_1_0p333_0","t":0,"s":[205.052,648.436],"e":[237.052,616.436],"to":[5.33333349227905,-5.33333349227905],"ti":[-5.33333349227905,5.33333349227905]},{"i":{"x":0.833,"y":0.833},"o":{"x":0.333,"y":0.333},"n":"0p833_0p833_0p333_0p333","t":30,"s":[237.052,616.436],"e":[237.052,616.436],"to":[0,0],"ti":[0,0]},{"i":{"x":0.667,"y":1},"o":{"x":0.333,"y":0},"n":"0p667_1_0p333_0","t":62,"s":[237.052,616.436],"e":[242.052,611.436],"to":[0.83333331346512,-0.83333331346512],"ti":[-0.83333331346512,0.83333331346512]},{"i":{"x":0.667,"y":0.667},"o":{"x":0.167,"y":0.167},"n":"0p667_0p667_0p167_0p167","t":77,"s":[242.052,611.436],"e":[242.052,611.436],"to":[0,0],"ti":[0,0]},{"i":{"x":0.667,"y":1},"o":{"x":0.167,"y":0},"n":"0p667_1_0p167_0","t":157,"s":[242.052,611.436],"e":[237.052,616.436],"to":[-0.83333331346512,0.83333331346512],"ti":[0.83333331346512,-0.83333331346512]},{"i":{"x":0.667,"y":0.667},"o":{"x":0.167,"y":0.167},"n":"0p667_0p667_0p167_0p167","t":169,"s":[237.052,616.436],"e":[237.052,616.436],"to":[0,0],"ti":[0,0]},{"i":{"x":0.667,"y":1},"o":{"x":0.167,"y":0},"n":"0p667_1_0p167_0","t":264,"s":[237.052,616.436],"e":[243.052,610.436],"to":[1,-1],"ti":[-1,1]},{"t":277}],"ix":2},"a":{"a":0,"k":[0,0],"ix":1},"s":{"a":0,"k":[100,100],"ix":3},"r":{"a":0,"k":0,"ix":6},"o":{"a":0,"k":100,"ix":7},"sk":{"a":0,"k":0,"ix":4},"sa":{"a":0,"k":0,"ix":5},"nm":"Transform"}],"nm":"Group 16","np":2,"cix":2,"ix":15,"mn":"ADBE Vector Group","hd":false},{"ty":"gr","it":[{"ind":0,"ty":"sh","ix":1,"ks":{"a":0,"k":{"i":[[5.041,-28.911],[-26.046,-5.185],[-5.035,28.9],[26.036,5.181]],"o":[[-5.05,28.896],[26.036,5.179],[5.046,-28.897],[-26.033,-5.187]],"v":[[-47.128,-7.596],[-9.122,50.552],[47.132,11.171],[9.139,-50.543]],"c":true},"ix":2},"nm":"Path 1","mn":"ADBE Vector Shape - Group","hd":false},{"ty":"fl","c":{"a":0,"k":[0.827000038297,0.57599995931,0.442999985639,1],"ix":4},"o":{"a":0,"k":100,"ix":5},"r":1,"nm":"Fill 1","mn":"ADBE Vector Graphic - Fill","hd":false},{"ty":"tr","p":{"a":1,"k":[{"i":{"x":0.833,"y":1},"o":{"x":0.333,"y":0},"n":"0p833_1_0p333_0","t":0,"s":[480.981,648.436],"e":[512.981,616.436],"to":[5.33333349227905,-5.33333349227905],"ti":[-5.33333349227905,5.33333349227905]},{"i":{"x":0.833,"y":0.833},"o":{"x":0.333,"y":0.333},"n":"0p833_0p833_0p333_0p333","t":30,"s":[512.981,616.436],"e":[512.981,616.436],"to":[0,0],"ti":[0,0]},{"i":{"x":0.667,"y":1},"o":{"x":0.333,"y":0},"n":"0p667_1_0p333_0","t":62,"s":[512.981,616.436],"e":[516.981,621.436],"to":[0.66666668653488,0.83333331346512],"ti":[-0.66666668653488,-0.83333331346512]},{"i":{"x":0.667,"y":0.667},"o":{"x":0.167,"y":0.167},"n":"0p667_0p667_0p167_0p167","t":77,"s":[516.981,621.436],"e":[516.981,621.436],"to":[0,0],"ti":[0,0]},{"i":{"x":0.667,"y":1},"o":{"x":0.167,"y":0},"n":"0p667_1_0p167_0","t":157,"s":[516.981,621.436],"e":[513,616.436],"to":[-0.66357421875,-0.83332985639572],"ti":[0.66357421875,0.83332985639572]},{"i":{"x":0.667,"y":0.667},"o":{"x":0.167,"y":0.167},"n":"0p667_0p667_0p167_0p167","t":169,"s":[513,616.436],"e":[513,616.436],"to":[0,0],"ti":[0,0]},{"i":{"x":0.667,"y":1},"o":{"x":0.167,"y":0},"n":"0p667_1_0p167_0","t":264,"s":[513,616.436],"e":[519,610.436],"to":[1,-1],"ti":[-1,1]},{"t":277}],"ix":2},"a":{"a":0,"k":[0,0],"ix":1},"s":{"a":0,"k":[100,100],"ix":3},"r":{"a":0,"k":0,"ix":6},"o":{"a":0,"k":100,"ix":7},"sk":{"a":0,"k":0,"ix":4},"sa":{"a":0,"k":0,"ix":5},"nm":"Transform"}],"nm":"Group 17","np":2,"cix":2,"ix":16,"mn":"ADBE Vector Group","hd":false},{"ty":"gr","it":[{"ind":0,"ty":"sh","ix":1,"ks":{"a":0,"k":{"i":[[27.631,-38.545],[-1.547,2.843],[-2.942,16.183],[0,0],[0,5.792]],"o":[[-27.628,38.542],[1.546,-2.842],[2.945,-16.184],[-3.029,-3.936],[40.798,-1.165]],"v":[[20.527,10.851],[-46.611,59.785],[-3.228,-17.814],[-9.245,-43.003],[-11.344,-61.462]],"c":true},"ix":2},"nm":"Path 1","mn":"ADBE Vector Shape - Group","hd":false},{"ty":"fl","c":{"a":0,"k":[0.529411764706,0.258823529412,0.882352941176,1],"ix":4},"o":{"a":0,"k":100,"ix":5},"r":1,"nm":"Fill 1","mn":"ADBE Vector Graphic - Fill","hd":false},{"ty":"tr","p":{"a":1,"k":[{"i":{"x":0.667,"y":1},"o":{"x":0.333,"y":0},"n":"0p667_1_0p333_0","t":0,"s":[386.1,897.487],"e":[418.1,865.487],"to":[5.33333349227905,-5.33333349227905],"ti":[-5.33333349227905,5.33333349227905]},{"t":30}],"ix":2},"a":{"a":0,"k":[0,0],"ix":1},"s":{"a":0,"k":[100,100],"ix":3},"r":{"a":0,"k":0,"ix":6},"o":{"a":0,"k":100,"ix":7},"sk":{"a":0,"k":0,"ix":4},"sa":{"a":0,"k":0,"ix":5},"nm":"Transform"}],"nm":"Group 18","np":2,"cix":2,"ix":17,"mn":"ADBE Vector Group","hd":false},{"ty":"gr","it":[{"ind":0,"ty":"sh","ix":1,"ks":{"a":0,"k":{"i":[[-27.628,-38.545],[1.546,2.843],[2.944,16.183],[0,0],[0,5.792]],"o":[[27.629,38.542],[-1.547,-2.842],[-2.944,-16.184],[3.027,-3.936],[-40.799,-1.165]],"v":[[-20.528,10.851],[46.611,59.785],[3.226,-17.814],[9.245,-43.003],[11.342,-61.462]],"c":true},"ix":2},"nm":"Path 1","mn":"ADBE Vector Shape - Group","hd":false},{"ty":"fl","c":{"a":0,"k":[0.529411764706,0.258823529412,0.882352941176,1],"ix":4},"o":{"a":0,"k":100,"ix":5},"r":1,"nm":"Fill 1","mn":"ADBE Vector Graphic - Fill","hd":false},{"ty":"tr","p":{"a":1,"k":[{"i":{"x":0.667,"y":1},"o":{"x":0.333,"y":0},"n":"0p667_1_0p333_0","t":0,"s":[294.88,895.487],"e":[324.88,865.487],"to":[5,-5],"ti":[-5,5]},{"t":30}],"ix":2},"a":{"a":0,"k":[0,0],"ix":1},"s":{"a":0,"k":[100,100],"ix":3},"r":{"a":0,"k":0,"ix":6},"o":{"a":0,"k":100,"ix":7},"sk":{"a":0,"k":0,"ix":4},"sa":{"a":0,"k":0,"ix":5},"nm":"Transform"}],"nm":"Group 7","np":2,"cix":2,"ix":18,"mn":"ADBE Vector Group","hd":false},{"ty":"gr","it":[{"ind":0,"ty":"sh","ix":1,"ks":{"a":0,"k":{"i":[[0,0],[0,0],[0,0],[0,0],[0,0]],"o":[[0,0],[0,0],[0,0],[0,0],[0,0]],"v":[[-5.675,-48.732],[0.002,-45.655],[5.675,-48.732],[5.675,48.732],[-5.675,48.732]],"c":true},"ix":2},"nm":"Path 1","mn":"ADBE Vector Shape - Group","hd":false},{"ty":"fl","c":{"a":0,"k":[0.192156862745,0.01568627451,0.466666666667,1],"ix":4},"o":{"a":0,"k":100,"ix":5},"r":1,"nm":"Fill 1","mn":"ADBE Vector Graphic - Fill","hd":false},{"ty":"tr","p":{"a":1,"k":[{"i":{"x":0.667,"y":1},"o":{"x":0.333,"y":0},"n":"0p667_1_0p333_0","t":0,"s":[339.49,1003.173],"e":[371.49,971.173],"to":[5.33333349227905,-5.33333349227905],"ti":[-5.33333349227905,5.33333349227905]},{"t":30}],"ix":2},"a":{"a":0,"k":[0,0],"ix":1},"s":{"a":0,"k":[100,100],"ix":3},"r":{"a":0,"k":0,"ix":6},"o":{"a":0,"k":100,"ix":7},"sk":{"a":0,"k":0,"ix":4},"sa":{"a":0,"k":0,"ix":5},"nm":"Transform"}],"nm":"Group 19","np":2,"cix":2,"ix":19,"mn":"ADBE Vector Group","hd":false},{"ty":"gr","it":[{"ind":0,"ty":"sh","ix":1,"ks":{"a":0,"k":{"i":[[-22.736,19.398],[7.676,-7.311],[-8.168,-66.31],[0,0],[0,0],[-6.229,14.989],[18.8,9.423],[13.054,-16.996],[0,0]],"o":[[-18.799,9.423],[6.23,14.989],[0,0],[0,0],[8.167,-66.31],[-7.676,-7.311],[24.065,20.532],[0,0],[-1.987,-5.687]],"v":[[-50.49,-94.633],[-145.512,-48.364],[-121.671,94.633],[0.001,94.633],[121.673,94.633],[145.512,-48.364],[50.492,-94.633],[0.001,-0.001],[-26.056,-31.814]],"c":true},"ix":2},"nm":"Path 1","mn":"ADBE Vector Shape - Group","hd":false},{"ty":"fl","c":{"a":0,"k":[0.262745098039,0,0.6,1],"ix":4},"o":{"a":0,"k":100,"ix":5},"r":1,"nm":"Fill 1","mn":"ADBE Vector Graphic - Fill","hd":false},{"ty":"tr","p":{"a":1,"k":[{"i":{"x":0.667,"y":1},"o":{"x":0.333,"y":0},"n":"0p667_1_0p333_0","t":0,"s":[339.489,957.273],"e":[371.489,925.273],"to":[5.33333349227905,-5.33333349227905],"ti":[-5.33333349227905,5.33333349227905]},{"t":30}],"ix":2},"a":{"a":0,"k":[0,0],"ix":1},"s":{"a":0,"k":[100,100],"ix":3},"r":{"a":0,"k":0,"ix":6},"o":{"a":0,"k":100,"ix":7},"sk":{"a":0,"k":0,"ix":4},"sa":{"a":0,"k":0,"ix":5},"nm":"Transform"}],"nm":"Group 20","np":2,"cix":2,"ix":20,"mn":"ADBE Vector Group","hd":false},{"ty":"gr","it":[{"ind":0,"ty":"sh","ix":1,"ks":{"a":0,"k":{"i":[[0,0],[0,0],[0,0],[12.924,-7.908],[3.796,-1.333],[-30.635,-50.053],[0,0],[0,0],[-15.675,55.487],[0,0],[-0.02,15.219],[0,0]],"o":[[0,0],[0,0],[0.021,15.219],[0,0],[15.673,55.487],[0,0],[0,0],[30.637,-50.053],[-3.796,-1.333],[-12.924,-7.908],[0,0],[0,0]],"v":[[0,-116.959],[-35.268,-116.959],[-35.268,-92.473],[-50.477,-72.509],[-66.738,-59.932],[-9.099,116.959],[0,116.959],[9.096,116.959],[66.738,-59.932],[50.474,-72.509],[35.267,-92.473],[35.267,-116.959]],"c":true},"ix":2},"nm":"Path 1","mn":"ADBE Vector Shape - Group","hd":false},{"ty":"fl","c":{"a":0,"k":[0.827000038297,0.57599995931,0.442999985639,1],"ix":4},"o":{"a":0,"k":100,"ix":5},"r":1,"nm":"Fill 1","mn":"ADBE Vector Graphic - Fill","hd":false},{"ty":"tr","p":{"a":1,"k":[{"i":{"x":0.667,"y":1},"o":{"x":0.333,"y":0},"n":"0p667_1_0p333_0","t":0,"s":[339.49,934.946],"e":[371.49,902.946],"to":[5.33333349227905,-5.33333349227905],"ti":[-5.33333349227905,5.33333349227905]},{"t":30}],"ix":2},"a":{"a":0,"k":[0,0],"ix":1},"s":{"a":0,"k":[100,100],"ix":3},"r":{"a":0,"k":0,"ix":6},"o":{"a":0,"k":100,"ix":7},"sk":{"a":0,"k":0,"ix":4},"sa":{"a":0,"k":0,"ix":5},"nm":"Transform"}],"nm":"Group 21","np":2,"cix":2,"ix":21,"mn":"ADBE Vector Group","hd":false},{"ty":"gr","it":[{"ind":0,"ty":"sh","ix":1,"ks":{"a":0,"k":{"i":[[0,0],[0,0],[-3.404,-48.651],[0,0]],"o":[[3.365,-2.773],[33.446,12.137],[0,0],[0,0]],"v":[[-61.426,-30.015],[17.073,-71.692],[61.426,71.691],[-18.488,71.691]],"c":true},"ix":2},"nm":"Path 1","mn":"ADBE Vector Shape - Group","hd":false},{"ty":"fl","c":{"a":0,"k":[0.192156862745,0.01568627451,0.466666666667,1],"ix":4},"o":{"a":0,"k":100,"ix":5},"r":1,"nm":"Fill 1","mn":"ADBE Vector Graphic - Fill","hd":false},{"ty":"tr","p":{"a":1,"k":[{"i":{"x":0.667,"y":1},"o":{"x":0.333,"y":0},"n":"0p667_1_0p333_0","t":0,"s":[467.493,980.214],"e":[499.493,948.214],"to":[5.33333349227905,-5.33333349227905],"ti":[-5.33333349227905,5.33333349227905]},{"t":30}],"ix":2},"a":{"a":0,"k":[0,0],"ix":1},"s":{"a":0,"k":[100,100],"ix":3},"r":{"a":0,"k":0,"ix":6},"o":{"a":0,"k":100,"ix":7},"sk":{"a":0,"k":0,"ix":4},"sa":{"a":0,"k":0,"ix":5},"nm":"Transform"}],"nm":"Group 22","np":2,"cix":2,"ix":22,"mn":"ADBE Vector Group","hd":false},{"ty":"gr","it":[{"ind":0,"ty":"sh","ix":1,"ks":{"a":0,"k":{"i":[[0,0],[0,0],[3.406,-48.651],[0,0]],"o":[[-3.362,-2.773],[-33.447,12.137],[0,0],[0,0]],"v":[[61.426,-30.015],[-17.072,-71.692],[-61.426,71.691],[18.489,71.691]],"c":true},"ix":2},"nm":"Path 1","mn":"ADBE Vector Shape - Group","hd":false},{"ty":"fl","c":{"a":0,"k":[0.192156862745,0.01568627451,0.466666666667,1],"ix":4},"o":{"a":0,"k":100,"ix":5},"r":1,"nm":"Fill 1","mn":"ADBE Vector Graphic - Fill","hd":false},{"ty":"tr","p":{"a":1,"k":[{"i":{"x":0.667,"y":1},"o":{"x":0.333,"y":0},"n":"0p667_1_0p333_0","t":0,"s":[211.486,980.214],"e":[243.486,948.214],"to":[5.33333349227905,-5.33333349227905],"ti":[-5.33333349227905,5.33333349227905]},{"t":30}],"ix":2},"a":{"a":0,"k":[0,0],"ix":1},"s":{"a":0,"k":[100,100],"ix":3},"r":{"a":0,"k":0,"ix":6},"o":{"a":0,"k":100,"ix":7},"sk":{"a":0,"k":0,"ix":4},"sa":{"a":0,"k":0,"ix":5},"nm":"Transform"}],"nm":"Group 23","np":2,"cix":2,"ix":23,"mn":"ADBE Vector Group","hd":false}],"ip":-15,"op":60,"st":0,"bm":0},{"ddd":0,"ind":3,"ty":4,"nm":"Shape Layer 1","sr":1,"ks":{"o":{"a":1,"k":[{"i":{"x":[0.667],"y":[1]},"o":{"x":[0.333],"y":[0]},"n":["0p667_1_0p333_0"],"t":-15,"s":[0],"e":[100]},{"t":0}],"ix":11},"r":{"a":0,"k":0,"ix":10},"p":{"a":0,"k":[375,329,0],"ix":2},"a":{"a":0,"k":[0,0,0],"ix":1},"s":{"a":0,"k":[209.396,209.396,100],"ix":6}},"ao":0,"shapes":[{"ty":"gr","it":[{"ty":"rc","d":1,"s":{"a":0,"k":[212.926,351.648],"ix":2},"p":{"a":0,"k":[0,0],"ix":3},"r":{"a":0,"k":0,"ix":4},"nm":"Rectangle Path 1","mn":"ADBE Vector Shape - Rect","hd":false},{"ty":"st","c":{"a":0,"k":[1,1,1,1],"ix":3},"o":{"a":0,"k":100,"ix":4},"w":{"a":0,"k":0,"ix":5},"lc":1,"lj":1,"ml":4,"ml2":{"a":0,"k":4,"ix":8},"nm":"Stroke 1","mn":"ADBE Vector Graphic - Stroke","hd":false},{"ty":"fl","c":{"a":0,"k":[0.2,0.2,0.2,1],"ix":4},"o":{"a":0,"k":100,"ix":5},"r":1,"nm":"Fill 1","mn":"ADBE Vector Graphic - Fill","hd":false},{"ty":"tr","p":{"a":0,"k":[-0.037,60.324],"ix":2},"a":{"a":0,"k":[0,0],"ix":1},"s":{"a":0,"k":[100,100],"ix":3},"r":{"a":0,"k":0,"ix":6},"o":{"a":0,"k":100,"ix":7},"sk":{"a":0,"k":0,"ix":4},"sa":{"a":0,"k":0,"ix":5},"nm":"Transform"}],"nm":"Rectangle 1","np":3,"cix":2,"ix":1,"mn":"ADBE Vector Group","hd":false}],"ip":-15,"op":60,"st":0,"bm":0}],"markers":[]}